tk_toolkit/__init__.py
tk_toolkit/tk_toolkit.py
tk_toolkit-1.0.3.dist-info/LICENSE
tk_toolkit-1.0.3.dist-info/METADATA
tk_toolkit-1.0.3.dist-info/WHEEL
tk_toolkit-1.0.3.dist-info/top_level.txt
tk_toolkit-1.0.3.dist-info/RECORD
