Metadata-Version: 2.1
Name: tk_toolkit
Version: 1.0.3
Summary: Toolkit for tkinter
Home-page: https://github.com/Jonathan-0101/tk-toolkit
Author: Jonathan Woolf & Matthew Kayne
Author-email: jonathan.woolf.01@gmail.com
License: UNKNOWN
Platform: UNKNOWN
License-File: LICENSE
